llmshark/__init__.py
llmshark/advanced_visualization.py
llmshark/analyzer.py
llmshark/cli.py
llmshark/comparator.py
llmshark/dashboard_app.py
llmshark/models.py
llmshark/parser.py
llmshark/streamlit_dashboard.py
llmshark/visualization.py
llmshark-0.1.0.dist-info/METADATA
llmshark-0.1.0.dist-info/WHEEL
llmshark-0.1.0.dist-info/entry_points.txt
llmshark-0.1.0.dist-info/licenses/LICENSE
llmshark-0.1.0.dist-info/RECORD
