Metadata-Version: 2.4
Name: llmshark
Version: 0.1.0
Summary: Comprehensive analysis tool for LLM streaming traffic from PCAP files
Project-URL: Homepage, https://github.com/llmshark/llmshark
Project-URL: Documentation, https://llmshark.readthedocs.io
Project-URL: Repository, https://github.com/llmshark/llmshark
Project-URL: Issues, https://github.com/llmshark/llmshark/issues
Author: Anthony Casagrande
License: MIT
License-File: LICENSE
Keywords: analysis,http,llm,pcap,sse,streaming,wireshark
Classifier: Development Status :: 3 - Alpha
Classifier: Environment :: Console
Classifier: Intended Audience :: Developers
Classifier: Intended Audience :: System Administrators
Classifier: License :: OSI Approved :: MIT License
Classifier: Operating System :: OS Independent
Classifier: Programming Language :: Python :: 3
Classifier: Programming Language :: Python :: 3.10
Classifier: Programming Language :: Python :: 3.11
Classifier: Programming Language :: Python :: 3.12
Classifier: Topic :: Internet :: WWW/HTTP :: HTTP Servers
Classifier: Topic :: Software Development :: Testing
Classifier: Topic :: System :: Networking :: Monitoring
Requires-Python: >=3.10
Requires-Dist: altair>=5.0.0
Requires-Dist: bokeh>=3.2.0
Requires-Dist: click>=8.0.0
Requires-Dist: dash-bootstrap-components>=1.5.0
Requires-Dist: dash>=2.14.0
Requires-Dist: httpx>=0.24.0
Requires-Dist: kaleido>=0.2.1
Requires-Dist: matplotlib>=3.7.0
Requires-Dist: networkx>=3.1.0
Requires-Dist: numpy>=1.24.0
Requires-Dist: pandas>=2.0.0
Requires-Dist: pillow>=10.0.0
Requires-Dist: plotly>=5.15.0
Requires-Dist: pydantic>=2.0.0
Requires-Dist: python-dateutil>=2.8.0
Requires-Dist: rich>=13.0.0
Requires-Dist: scapy>=2.5.0
Requires-Dist: scikit-learn>=1.3.0
Requires-Dist: scipy>=1.10.0
Requires-Dist: seaborn>=0.12.0
Requires-Dist: statsmodels>=0.14.0
Requires-Dist: streamlit>=1.28.0
Requires-Dist: tabulate>=0.9.0
Requires-Dist: typer>=0.9.0
Provides-Extra: dev
Requires-Dist: black>=23.0.0; extra == 'dev'
Requires-Dist: build>=0.10.0; extra == 'dev'
Requires-Dist: mypy>=1.5.0; extra == 'dev'
Requires-Dist: pre-commit>=3.3.0; extra == 'dev'
Requires-Dist: pytest-asyncio>=0.21.0; extra == 'dev'
Requires-Dist: pytest-cov>=4.1.0; extra == 'dev'
Requires-Dist: pytest-mock>=3.11.0; extra == 'dev'
Requires-Dist: pytest>=7.4.0; extra == 'dev'
Requires-Dist: ruff>=0.0.280; extra == 'dev'
Requires-Dist: twine>=4.0.0; extra == 'dev'
Provides-Extra: test
Requires-Dist: pytest-asyncio>=0.21.0; extra == 'test'
Requires-Dist: pytest-cov>=4.1.0; extra == 'test'
Requires-Dist: pytest-mock>=3.11.0; extra == 'test'
Requires-Dist: pytest>=7.4.0; extra == 'test'
